pydantic_cloud_configuration/__init__.py
pydantic_cloud_configuration/aws/__init__.py
pydantic_cloud_configuration/aws/parameter_store.py
pydantic_cloud_configuration/aws/secrets_manager.py
pydantic_cloud_configuration/cloud_base_settings.py
pydantic_cloud_configuration/cloud_settings.py
pydantic_cloud_configuration/py.typed
pydantic_cloud_configuration-0.0.3.dist-info/entry_points.txt
pydantic_cloud_configuration-0.0.3.dist-info/LICENSE
pydantic_cloud_configuration-0.0.3.dist-info/WHEEL
pydantic_cloud_configuration-0.0.3.dist-info/METADATA
pydantic_cloud_configuration-0.0.3.dist-info/RECORD
