Metadata-Version: 2.1
Name: pydantic-cloud-configuration
Version: 0.0.3
Summary: Pydantic Cloud Settings
Home-page: https://github.com/nilsdebruin/pydantic-cloud-configuration
License: MIT
Author: Nils de Bruin
Author-email: nils@debruinmail.nl
Requires-Python: >=3.7,<4.0
Classifier: Development Status :: 3 - Alpha
Classifier: License :: OSI Approved :: MIT License
Classifier: Programming Language :: Python :: 3
Classifier: Programming Language :: Python :: 3.10
Classifier: Programming Language :: Python :: 3.7
Classifier: Programming Language :: Python :: 3.8
Classifier: Programming Language :: Python :: 3.9
Requires-Dist: pydantic[dotenv] (>=1.9.0,<2.0.0)
Project-URL: Changelog, https://github.com/nilsdebruin/pydantic-cloud-configuration/releases
Project-URL: Documentation, https://pydantic-cloud-configuration.readthedocs.io
Project-URL: Repository, https://github.com/nilsdebruin/pydantic-cloud-configuration
